LAB-03/mux_4_1_logic.v
module mux_4_1_logic (
    input [3:0] IN,
    input [1:0] sel,
    input EN,
    output reg e
);

    always @(*) begin
    	if (~EN)
    		e = 4'b0000;
    	else begin
		case(sel)
		    2'b00: e = IN[0];
		    2'b01: e = IN[1];
		    2'b10: e = IN[2];
		    2'b11: e = IN[3];
		    default: e = 4'b0000;
		endcase
	end
    end
endmodule

LAB-03/mux_4_1_tb.v
`include "mux_4_1_logic.v"
`timescale 1ns/1ps // time unit / simulation precision

module mux_4_1_tb;

    reg [3:0] IN;
    reg [1:0] S;
    reg EN;
    wire Y;
    
    mux_4_1_logic uut (.IN(IN), .sel(S), .e(Y));
    
    initial begin
        $dumpfile ("mux_4_1_tb.vcd");
        $dumpvars (0 , mux_4_1_tb);
    end
    
    initial begin
        // 10 Test cases
        // 1
        EN = 1; IN = 4'b0000; S = 2'b00; #10;
        // 2
        EN = 1; IN = 4'b0000; S = 2'b01; #10;
        // 3
        EN = 1; IN = 4'b0000; S = 2'b10; #10;
        // 4
        EN = 1; IN = 4'b0000; S = 2'b11; #10;
        // 5
        EN = 1; IN = 4'b1111; S = 2'b00; #10;
        // 6
        EN = 1; IN = 4'b1111; S = 2'b01; #10;
        // 7
        EN = 1; IN = 4'b1111; S = 2'b10; #10;
        // 8
        EN = 1; IN = 4'b1111; S = 2'b11; #10;
        // 9
        EN = 0; IN = 4'b0000; S = 2'b00; #10;
        // 10
        EN = 0; IN = 4'b1111; S = 2'b11; #10;
    end

endmodule

LAB-03/mux_4_1_tb.vcd
$date
	Tue Aug 29 09:34:32 2023
$end
$version
	Icarus Verilog
$end
$timescale
	1ps
$end
$scope module mux_4_1_tb $end
$var wire 1 ! Y $end
$var reg 1 " EN $end
$var reg 4 # IN [3:0] $end
$var reg 2 $ S [1:0] $end
$scope module uut $end
$var wire 1 % EN $end
$var wire 4 & IN [3:0] $end
$var wire 2 ' sel [1:0] $end
$var reg 1 ! e $end
$upscope $end
$upscope $end
$enddefinitions $end
#0
$dumpvars
b0 '
b0 &
z%
b0 $
b0 #
1"
0!
$end
#10000
b1 $
b1 '
#20000
b10 $
b10 '
#30000
b11 $
b11 '
#40000
1!
b0 $
b0 '
b1111 #
b1111 &
#50000
b1 $
b1 '
#60000
b10 $
b10 '
#70000
b11 $
b11 '
#80000
0!
b0 $
b0 '
b0 #
b0 &
0"
#90000
1!
b11 $
b11 '
b1111 #
b1111 &
