LAB-04/frequency_divider.v
module frequency_divider (
  // Inputs
  input clk,
  input rst_btn,

  // Outputs
  output reg [3:0] out_clk
);

  wire rst;
  reg [31:0] count;
  localparam [31:0] max_count = (1) - 1;

  // Reset é o inverso do botão de reset
  assign rst = ~rst_btn;

  // Divisor de clock
  always @(posedge clk or posedge rst) begin
    if (rst) begin
      out_clk <= 4'b0;
      count <= 32'b0;
    end
    else if (count == max_count) begin
      count <= 32'b0;
      out_clk <= out_clk + 1'b1;
    end
    else begin
      count <= count + 1;
    end
  end

endmodule

LAB-04/frequency_divider_tb.v
`timescale 10ns/1ps
`include "frequency_divider.v"

module frequency_divider_tb;

  output reg clk, rst;
  input wire [3:0] out_clk;

  frequency_divider uut(clk, rst, out_clk);

  initial
    clk = 1'b0;

  always
    #1 clk = ~clk;

  initial begin
    $monitor($time, "clk = %b, rst = %b, out_clk = %b", clk, rst, out_clk);

    rst = 0;
    #1 rst = 1;
    #31 $finish;
  end

  initial begin
    $dumpfile("frequency_divider_tb.vcd");
    $dumpvars(0, frequency_divider_tb);
  end

endmodule

LAB-04/frequency_divider_tb.vcd
$date
	Mon Sep 11 18:50:17 2023
$end
$version
	Icarus Verilog
$end
$timescale
	1ps
$end
$scope module frequency_divider_tb $end
$var wire 4 ! out_clk [3:0] $end
$var reg 1 " clk $end
$var reg 1 # rst $end
$scope module uut $end
$var wire 1 " clk $end
$var wire 1 $ rst $end
$var wire 1 # rst_btn $end
$var reg 32 % count [31:0] $end
$var reg 4 & out_clk [3:0] $end
$upscope $end
$upscope $end
$enddefinitions $end
#0
$dumpvars
b0 &
b0 %
1$
0#
0"
b0 !
$end
#10000
0$
1#
1"
#20000
0"
#30000
b1 !
b1 &
1"
#40000
0"
#50000
b10 !
b10 &
1"
#60000
0"
#70000
b11 !
b11 &
1"
#80000
0"
#90000
b100 !
b100 &
1"
#100000
0"
#110000
b101 !
b101 &
1"
#120000
0"
#130000
b110 !
b110 &
1"
#140000
0"
#150000
b111 !
b111 &
1"
#160000
0"
#170000
b1000 !
b1000 &
1"
#180000
0"
#190000
b1001 !
b1001 &
1"
#200000
0"
#210000
b1010 !
b1010 &
1"
#220000
0"
#230000
b1011 !
b1011 &
1"
#240000
0"
#250000
b1100 !
b1100 &
1"
#260000
0"
#270000
b1101 !
b1101 &
1"
#280000
0"
#290000
b1110 !
b1110 &
1"
#300000
0"
#310000
b1111 !
b1111 &
1"
