LAB-02/full_adder.v
module full_adder(
    // Port declarations
        // Inputs
        input a,
        input b,
        input cin,
        // Outputs
        output s,
        output cout
    );

    // Declaration of internal wires
    wire w1, w2, w3;
    
    // Circuit operations - structural approach
    xor u0 (w1, a, b);
    xor u1 (s, w1, cin);
    and u2 (w2, a, b);
    and u3 (w3, a, b);
    or u4 (cout, w2, w3);

endmodule

LAB-02/full_adder_tb.v
// tp for full adder

`include "full_adder.v"

module full_adder_tb;

    reg A, B, CIN;
    wire S, COUT;

    // full adder instance
    full_adder uut(.a(A), .b(B), .cin(CIN), .s(S), .cout(COUT));

    initial begin
        $dumpfile("full_adder_tb.vcd");
        $dumpvars(0, full_adder_tb);
    end

    initial begin
        A = 1'b0; B = 1'b0; CIN = 1'b0; #1;
        A = 1'b0; B = 1'b0; CIN = 1'b1; #1;
        A = 1'b0; B = 1'b1; CIN = 1'b0; #1;
        A = 1'b0; B = 1'b1; CIN = 1'b1; #1;
        A = 1'b1; B = 1'b0; CIN = 1'b0; #1;
        A = 1'b1; B = 1'b0; CIN = 1'b1; #1;
        A = 1'b1; B = 1'b1; CIN = 1'b0; #1;
        A = 1'b1; B = 1'b1; CIN = 1'b1; #1;
    end

endmodule

LAB-02/full_adder_tb.vcd
$date
	Mon Aug 14 15:50:25 2023
$end
$version
	Icarus Verilog
$end
$timescale
	1s
$end
$scope module full_adder_tb $end
$var wire 1 ! S $end
$var wire 1 " COUT $end
$var reg 1 # A $end
$var reg 1 $ B $end
$var reg 1 % CIN $end
$scope module uut $end
$var wire 1 # a $end
$var wire 1 $ b $end
$var wire 1 % cin $end
$var wire 1 " cout $end
$var wire 1 ! s $end
$var wire 1 & w1 $end
$var wire 1 ' w2 $end
$var wire 1 ( w3 $end
$upscope $end
$upscope $end
$enddefinitions $end
#0
$dumpvars
0(
0'
0&
0%
0$
0#
0"
0!
$end
#1
1!
1%
#2
1&
0%
1$
#3
0!
1%
#4
1!
0%
0$
1#
#5
0!
1%
#6
1"
0&
1'
1(
0%
1$
#7
1!
1%
